encoding/__init__.py
encoding/cliffordt2cnf.py
encoding/cliffordt2cnf_py_codegen.py
encoding/cnf.py
encoding/memory.py
encoding/qasm2cnf.py
encoding/qasm_parser.py
quokka_sharp-0.0.1.dist-info/METADATA
quokka_sharp-0.0.1.dist-info/WHEEL
quokka_sharp-0.0.1.dist-info/top_level.txt
quokka_sharp-0.0.1.dist-info/RECORD
